[
	{
		"time": "2013-01-20T20:00:00.001Z",
		"a": 12,
		"b": 4,
		"c": 20
	},
	{
		"time": "2013-01-20T21:00:00.001Z",
		"a": 23,
		"b": 0,
		"c": 27
	},
	{
		"time": "2013-01-20T22:00:00.001Z",
		"a": 14,
		"b": 5,
		"c": 19
	},
	{
		"time": "2013-01-20T23:00:00.001Z",
		"a": 18,
		"b": 6,
		"c": 10
	},
	{
		"time": "2013-01-21T00:00:00.001Z",
		"a": 11,
		"b": 1,
		"c": 9
	},
	{
		"time": "2013-01-21T01:00:00.001Z",
		"a": 13,
		"b": 10,
		"c": 29
	},
	{
		"time": "2013-01-21T02:00:00.001Z",
		"a": 20,
		"b": 2,
		"c": 24
	},
	{
		"time": "2013-01-21T03:00:00.001Z",
		"a": 3,
		"b": 1,
		"c": 10
	}
]